govee_h6199_ble/__init__.py
govee_h6199_ble/base.py
govee_h6199_ble/commands.py
govee_h6199_ble/const.py
govee_h6199_ble/device.py
govee_h6199_ble/model.py
govee_h6199_ble/packet.py
govee_h6199_ble/util.py
govee_h6199_ble-1.0.0.dist-info/METADATA
govee_h6199_ble-1.0.0.dist-info/WHEEL
govee_h6199_ble-1.0.0.dist-info/licenses/LICENSE
govee_h6199_ble-1.0.0.dist-info/RECORD
