Metadata-Version: 2.4
Name: govee-h6199-ble
Version: 1.0.0
Summary: Manage Govee DreamView T1 (H6199) BLE devices
License: Copyright (c) 2024 Mikalai Kukhta and individual contributors.
License-File: LICENSE
Keywords: ble,govee,h6199,dreamview
Author: Mikalai Kukhta
Author-email: mikalai.kukhta@gmail.com
Requires-Python: >=3.11,<4.0
Classifier: Development Status :: 3 - Alpha
Classifier: Intended Audience :: Developers
Classifier: License :: OSI Approved :: MIT License
Classifier: Natural Language :: English
Classifier: Operating System :: OS Independent
Classifier: Programming Language :: Python :: 3
Classifier: Programming Language :: Python :: 3.11
Classifier: Programming Language :: Python :: 3.12
Classifier: Programming Language :: Python :: 3.13
Classifier: Topic :: Software Development :: Libraries
Requires-Dist: bleak (>=0.15.1)
Project-URL: Issues, https://github.com/NecroKote/pygovee-h6199-ble/issues
Project-URL: Repository, https://github.com/NecroKote/pygovee-h6199-ble
